tgtg_msg/__init__.py
tgtg_msg/comm/__init__.py
tgtg_msg/comm/parse_tuple.py
tgtg_msg/comm/print_env.py
tgtg_msg/version.py
tgtg_msg-0.1.7.dist-info/entry_points.txt
tgtg_msg-0.1.7.dist-info/LICENSE
tgtg_msg-0.1.7.dist-info/METADATA
tgtg_msg-0.1.7.dist-info/WHEEL
tgtg_msg-0.1.7.dist-info/RECORD
